multimodal_transformers/__init__.py
multimodal_transformers/data/__init__.py
multimodal_transformers/data/data_utils.py
multimodal_transformers/data/load_data.py
multimodal_transformers/data/tabular_torch_dataset.py
multimodal_transformers/model/__init__.py
multimodal_transformers/model/layer_utils.py
multimodal_transformers/model/tabular_combiner.py
multimodal_transformers/model/tabular_config.py
multimodal_transformers/model/tabular_modeling_auto.py
multimodal_transformers/model/tabular_transformers.py
multimodal_transformers/multimodal_arguments/__init__.py
multimodal_transformers/multimodal_arguments/multimodal_arguments.py
multimodal_transformers-0.4.0.dist-info/LICENSE
multimodal_transformers-0.4.0.dist-info/METADATA
multimodal_transformers-0.4.0.dist-info/WHEEL
multimodal_transformers-0.4.0.dist-info/top_level.txt
multimodal_transformers-0.4.0.dist-info/RECORD
